lark/__init__.py
lark/common.py
lark/exceptions.py
lark/grammar.py
lark/indenter.py
lark/lark.py
lark/lexer.py
lark/load_grammar.py
lark/parse_tree_builder.py
lark/parser_frontends.py
lark/reconstruct.py
lark/tree.py
lark/utils.py
lark/visitors.py
lark/grammars/common.lark
lark/parsers/__init__.py
lark/parsers/cyk.py
lark/parsers/earley.py
lark/parsers/grammar_analysis.py
lark/parsers/lalr_analysis.py
lark/parsers/lalr_parser.py
lark/parsers/resolve_ambig.py
lark/parsers/xearley.py
lark/tools/__init__.py
lark/tools/nearley.py
lark/tools/standalone.py
lark067-0.6.7.dist-info/LICENSE
lark067-0.6.7.dist-info/METADATA
lark067-0.6.7.dist-info/WHEEL
lark067-0.6.7.dist-info/top_level.txt
lark067-0.6.7.dist-info/RECORD
